kdict/__init__.py
kdict/core.py
kdict/helpers.py
kdict-0.1.0.dist-info/LICENSE
kdict-0.1.0.dist-info/METADATA
kdict-0.1.0.dist-info/WHEEL
kdict-0.1.0.dist-info/top_level.txt
kdict-0.1.0.dist-info/RECORD
