Metadata-Version: 2.1
Name: kdict
Version: 0.1.0
Summary: Kdict
Home-page: https://github.com/maximz/kdict
Author: Maxim Zaslavsky
Author-email: maxim@maximz.com
License: MIT license
Platform: UNKNOWN
Classifier: Development Status :: 2 - Pre-Alpha
Classifier: Intended Audience :: Developers
Classifier: License :: OSI Approved :: MIT License
Classifier: Natural Language :: English
Classifier: Programming Language :: Python :: 3
Classifier: Programming Language :: Python :: 3.6
Classifier: Programming Language :: Python :: 3.7
Classifier: Programming Language :: Python :: 3.8
Requires-Python: >=3.7
License-File: LICENSE
Requires-Dist: Click (>=7.0)
